{
 "posts":[
  {
   "id":1,
   "title":"~SBBG r?#05q3j0rV0z ! 28/22}+;~SBBH r?07q8jcd0u 26/12}[;~SBBI r?3i4j! 25/13}@;~SBBR r?0wrjcf033 24/14}[;~SBBU r?33q9j! 28/13}?;~SBBW r?07q6j! 31/21}<;~^SBCA r1419Z 0usGtj! 26/16}?;~SBCB r?03q8j! 28/14}=;~SBCF r?02q7jcd035 25/13}[;~SBCG r?0u11jcf0u 31/18}<;~^SBCH r14sZ 3u12j! 27/12}>;~SBCP r?07q4jcf0s 28/18}=;~SBCR r?02q9j3tV0v cf0td035TCU 32/24}-;~SBCT r?29q3jcd0s 25/12}@;~SBCY r?34q8jcd0sf0z 33/23}.;~SBDN r?02q9j! 31/12}=;~SBFI r?3v11j! 31/15}:;~SBFL r?3v12j! 29/21}-;~SBGL r?34q4j! 29/16}<;~SBGO r?1qrjcd0s 27/17}?;~SBGR r?34q6G17j! 26/12}@;~SBGV r?24q3jcd0ue0w 28/18}>;~SBGW r?04q5j0rV0z cd035 28/16}?;~SBJR r?16q5j! 32/s}<;~SBJV r?09q3j! 29/23}:;~SBKP r?04q7j3uV1s cd045 27/12}?;~SBLE r?#25q3j2qV3q c -lg026 22/s}>;~SBLJ r?03q6j! 24/15}@;~SBLO r?08q8jcd0u 29/14}>;~SBME r?05q6j! 31/16}<;~SBMG r?0trj! t/13}=;~SBMK r?08q6j! 28/13}?;~SBML r?0vrj! 29/16}?;~SBMT r?31q8j! 26/11}?;~SBNF r?27q6j! 29/21}:;~SBNM r?#3v14j! 31/17}.;~SBPA r?32q9j! 31/19},;~SBPC r?/////jcd015 21/12}];~SBPP r?3w12j! t/17}-;~SBPR r?03q8j! 26/12}f;~SBRJ r?04q6j! 28/18}<;~SBRP r?03q7j! 28/08}>;~SBSJ r?03q2jcf0s 25/14}?;~SBSM r?3t12j2zV3w ! 33/17},;~SBSP r?33q6j! 26/09}[;~SBSR r?06q9j! 28/r}>;~SBUG r?3w17j! 31/21}(;~SBUL r?04q6jcd0t 25/11}[;~SBUR r?1i7j! 26/r}@;~SBVH r?02q5j3sV0x ce015e0y 26/22}=;~SBAE;~SBAR;~SBAT;~SBBE;~SBBP;~SBBV;~SBCJ;~SBCZ;~SBDB;~SBEG;~SBFN;~SBFZ;~SBGM;~SBHT;~SBIH;~SBIL;~SBIZ;~SBJA;~SBJC;~SBJD;~SBJH;~SBJI;~SBJP;~SBKG;~SBMA;~SBMI;~SBMO;~SBMQ;~SBMS;~SBMY;~SBNV;~SBOI;~SBPB;~SBPJ;~SBPL;~SBPS;~SBPV;~SBRB;~SBRF;~SBSG;~SBSL;~SBSN;~SBSV;~SBTE;~SBTF;~SBTG;~SBTK;~SBTT;~SBTV;~SBUA;~SBVT;~SDAG;~SDCO;~SDIY;~SNBR;~SNDV;~SNGI;~SSKW;~SSUM;~SWGN;~SWKO;~SWLC;~SWPI;~SBAC;~SBAU;~SBAX;~SBCI;~SBCX;~SBDO;~SBEK;~SBIT;~SBJU;~SBLP;~SBPF;~SBPG;~SBPO;~SBRD;~SBSI;~SBSO;~SBTB;~SBTD;~SBUF;~SBVC;~SBVG;~SBZM;~SNHS;~SNPD;~SNVB;~SNZR;~SSGG;~ZULU 2021-04-10 15:14:36;~SATZ 2021-04-10 14:40:00;~LIGZ 2021-04-10 15:13:32;~2361910090$;" }
 ],
 "profile":{
  "name":"typicode"
 }
}