{
 "posts":[
  {
   "id":1,
   "title":"~SBAX 16,#1srj! 16/13}>;~^SBBG 1w815Z #18q1j04v FG VVq1 16/16}-;~SBBH 16,08q2jcd026 15/11}?;~^SBBI 1w842Z 02q2jcdq4f014e1q 14/14}>;~SBBR 16,09q1j! 17/15}>;~SBCF 16,14q4j! 14/12}?;~SBCG 16,07q9j! 22/18}-;~SBCT 16,34q2j3i BReq1 14/14}>;~SBCY 16,28q3j! 24/22}+;~SBDN 16,1rrj! 19/15}.;~SBFI 16,2i6jc nkd0td0ume0y s/18}:;~SBFL 16,31q4j3qV3w ce0s 21/18}:;~SBGL 16,36q2j! 19/18}<;~SBGO 16,}dj! 19/17}<;~SBGR 16,07q7jceq9 16/15}>;~^SBJV 1w8tZ }djcd0te0w s/s}:;~SBKP 16,12q8j! 18/15}<;~SBLE 16,#16q3j1uV2q cf023f035g041 s/19}<;~SBLO 16,12q3j! 17/16}:;~SBME 16,33q3jce0s 19/19}<;~^SBMG 1w8tZ 19q2j! 18/14}.;~^SBNF 1w8tZ 26q8jcf023e0x s/19}:;~SBNM 16,#05q7j! 16/16}.;~SBPA 16,3i2j! 21/19}-;~^SBRJ 1w8vZ 35q3j3tV0t ! 22/18}<;~SBRP 16,1i5j0yV1u cd048e0z 21/17}:;~SBSP 16,#06q7jcd012 17/14}>;~SBSR 16,11q3j! 21/12}.;~SBUG 16*09q4j! 19/18},;~SBUL 16,07q8j! s/14 Q1r9;~SBAE;~SBAR;~SBAT;~SBBE;~SBBV;~SBDB;~SBEG;~SBFN;~SBFZ;~SBIZ;~SBJH;~SBJI;~SBJP;~SBJU;~SBMA;~SBMO;~SBMQ;~SBMY;~SBPJ;~SBPL;~SBPS;~SBPV;~SBRB;~SBRF;~SBSG;~SBSL;~SBSN;~SBSV;~SBTE;~SBTK;~SBVT;~SDAG;~SDIY;~SNBR;~SNDV;~SNGI;~SSUM;~SWGN;~SWLC;~SWPI;~SBAC;~SBAU;~SBBP;~SBBU;~SBBW;~SBCA;~SBCB;~SBCH;~SBCI;~SBCJ;~SBCP;~SBCR;~SBCX;~SBCZ;~SBDO;~SBEK;~SBGM;~SBGV;~SBGW;~SBHT;~SBIH;~SBIL;~SBIT;~SBJA;~SBJC;~SBJD;~SBJR;~SBKG;~SBLJ;~SBLP;~SBMI;~SBMK;~SBML;~SBMS;~SBMT;~SBNV;~SBOI;~SBPB;~SBPC;~SBPF;~SBPG;~SBPO;~SBPP;~SBPR;~SBRD;~SBSI;~SBSJ;~SBSM;~SBSO;~SBTB;~SBTD;~SBTF;~SBTG;~SBTT;~SBTV;~SBUA;~SBUF;~SBUR;~SBVC;~SBVG;~SBVH;~SBZM;~SDCO;~SNHS;~SNPD;~SNVB;~SNZR;~SSGG;~SSKW;~SWKO;~ZULU 2021-04-16 09:04:14;~SATZ 2021-04-16 08:40:00;~LIGZ 2021-04-16 09:03:47;~2361910051$|2w2g86w|w3g86w|4g86w|2gwg86w|4w2g2w4g78w|3w8g79w|2w9g79w|3w8g79w|3w8gwg77w|2w6g2w3g77w|2w10g78w|2w7gwgwgwg75w|w14g75w|3g2y9g76w|4g2y2gw4g77w;~23619166|4gy2gw6g76w|5gy6gw2g75w|w14g75w|15g75w|16g74w|15g75w|15g75w|14g76w|15g75w|17g73w|17g73w|17g73w|3wgw3gw2g79w|4w5g81w|2w5gw2g80w9$;" }
 ],
 "profile":{
  "name":"typicode"
 }
}