{
 "posts":[
  {
   "id":1,
   "title":"~SBAX 07b#VRB02j! 21/12}@;~SBBG 07b#09q7jce036 14/11}@;~SBBH 07b1i4j! s/14}?;~SBBI 07b14q7jcgq7 14/13}f;~SBBR 07b16q3j! 22/13}@;~SBBU 07b13q4j! 18/17}?;~SBBW 07a}dj! 25/19}.;~^SBCA 072242Z 07q2j! 17/14}>;~SBCB 07b17q2j! 23/21}=;~SBCF 07b11q2j! s/14}?;~SBCG 07b06q7jc nkf045d0vmf1q 23/17}:;~SBCH 07b11q5jcd0t 18/16}>;~SBCP 07`15q4j! 23/s}<;~SBCR 07`05q5jcd0ud045TCUf1q 31/18}*;~SBCT 07b12q5jcgq5 14/14}f;~SBCY 07b3i2jcd0s 28/18},;~SBDN 07b11q4j! 18/18}=;~SBFI 07b27q2jcd0te0x 19/18}<;~SBFL 07b19q5jcd0te045g0v 17/15}[;~SBGL 07b15q6jcd0sg0u 23/s}<;~SBGO 07b12q4j! 24/13}=;~SBGR 07b17q3jcg011 18/17}@;~SBGV 07a}dj! 23/19}<;~SBGW 07aVRB04j14q kl BRfq4e0re0td035m 19/18}? pl;~SBIT 07`/////jcd0t 27/16}:;~^SBJR 072115Z 2i1jcd018e035 22/s}<;~SBJV 07b}dj25q leq4e0r 16/16}[;~SBKP 07b09q5jcdq2f025 18/18}@;~SBLE 07b#VRB02j! 21/s}=;~SBLO 07b08q3jcf015 18/18}?;~SBME 07b19q4j! 24/22}=;~SBMG 07b06q4jc nkdq5d0sm 18/17}<;~SBMK 07b13q5j! 25/13}=;~SBMT 07b16q3jce015 18/15}@;~SBNF 07b19q5jc -DZeq9e028 17/16}[;~SBNM 07b#12q4jcf026e036 19/17}=;~SBPA 07b1r14j4i -l BReq8g045 16/15}@;~SBPP 07`03q4j! 19/17}<;~SBRJ 07b17q9jcd0sf0u 23/21}<;~SBRP 07b1y11j1vV2r ! 23/17}=;~SBSJ 07b22q5jce021 18/16}@;~SBSM 07b0z11jcg017 16/14}?;~SBSP 07b15q5jcgq8 17/16}[;~SBSR 07b16q5j! 22/14}=;~SBUG 07a14q4j! 18/15}=;~SBUL 07b19q2j! 22/12}?;~SBUR 07b21q3j! 23/11}?;~SBVH 07b09q5j! 24/s}.;~SBAC;~SBAE;~SBAR;~SBBE;~SBBP;~SBBV;~SBCI;~SBCJ;~SBCZ;~SBDB;~SBEG;~SBFN;~SBFZ;~SBGM;~SBHT;~SBIH;~SBIL;~SBIZ;~SBJA;~SBJD;~SBJH;~SBJI;~SBJP;~SBJU;~SBKG;~SBMA;~SBMI;~SBMO;~SBMQ;~SBNV;~SBPJ;~SBPL;~SBPS;~SBPV;~SBRB;~SBRF;~SBSG;~SBSL;~SBSN;~SBSO;~SBSV;~SBTE;~SBTF;~SBTG;~SBTK;~SBTT;~SBVC;~SBVT;~SBZM;~SDCO;~SDIY;~SNBR;~SNDV;~SNGI;~SNHS;~SNZR;~SSGG;~SSKW;~SSUM;~SWGN;~SWKO;~SWLC;~SWPI;~SBAT;~SBAU;~SBCX;~SBDO;~SBEK;~SBJC;~SBLJ;~SBLP;~SBML;~SBMS;~SBMY;~SBOI;~SBPB;~SBPC;~SBPF;~SBPG;~SBPO;~SBPR;~SBRD;~SBSI;~SBTB;~SBTD;~SBTV;~SBUA;~SBUF;~SBVG;~SDAG;~SNPD;~SNVB;~ZULU 2021-06-07 23:37:22;~SATZ 2021-06-07 22:40:00;~LIGZ 2021-06-07 23:37:25;~2361910029$|15w5g70w|12w2g2ygy2g70w|10wg7y2g70w|6wW3w2g6yg71w|5w3W6w2g74w|6wW83w|W89w10$|13wW76w|W32w4W53w|3W29w4W54w|2W23w2W6w3W54w|W20wWw5W5wW56w|W14w5Ww3Ww5W3wWwW54w;~23619152|25wW64w|28w4W58w|27w5W58w|28wW61w|29wW60w$|33wW56w$|32w2W56w|26w7W57w|27w5W58w|27w4W59w|27wWw2W59w|30wW59w2$|15w2W73w|15w7W68w|13wW3w4W69w|13w4W2wW70w;~23619172|14wW75w17$;" }
 ],
 "profile":{
  "name":"typicode"
 }
}