{
 "posts":[
  {
   "id":1,
   "title":"~SBAX 27@#36q5j2zV0x ! t/16}>;~SBBG 27@#33q5j3qV0r cf017g037 24/s}-;~SBBH 27@32q4jcd0t 31/15}=;~SBBI 27@3i6jcf0u 29/19}=;~SBBR 27@05q5jcf0u 28/12}?;~SBBU 27@01q4jcd0u 33/s}:;~^SBBW 271615Z 3wrjcd0s 34/18}.;~SBCB 27@0v11j! 31/23}+;~SBCF 27@02q4jcf0u t/17}=;~SBCG 27@34q8jcf0u 32/18}:;~SBCP 27@11q5jcd0s 32/22}+;~SBCR 27@34q6j2xV0x cd0t 33/23}-;~SBCT 27@2zrjce045 29/18}=;~SBCY 27@01q6jcf0s 33/s}-;~SBDN 27@3q13jcf0ud0wTCU 34/17}.;~^SBFI 271637Z 35q7jc k nof0td0um 32/21},;~SBFL 27@1s11jcd0t 29/21},;~SBGL 27@35q4j! 34/22}*;~SBGO 27@VRB05jcd048 31/14}=;~SBGR 27@29q5j! 31/15}<;~SBGW 27@26q5j2rV3r cd035 32/21}:;~SBJR 27@16q8j! 36/24}*;~SBJV 27@12q6jcd0u 31/s}+;~SBKP 27@36q4jcd045 32/17}<;~SBLE 27@#13q6j0vV1z ! 31/17}.;~SBLJ 27@32q4jcf0t 24/18}>;~SBLO 27@28q3jcf0ud0vTCU 33/s}:;~SBME 27@1rrj! 32/25}+;~SBMG 27@3i8jcf0uf1q 32/21}.;~SBMK 27@04q6j! 32/16}<;~SBMT 27@28q5j2tV0s cd042 31/16}<;~SBNF 27@13q9jcd0s 29/22},;~SBNM 27@#17q3j1sV2r c -lgq4 s/s}:;~SBPA 27@28q8jcd012e0y 25/23}-;~SBPC 27@/////jcf0s 28/15}@;~SBPP 27@29q4jcd0s 31/16}<;~SBPR 27@32q5jcf0t 32/18}>;~SBRJ 27@03q3j! 32/25}*;~SBRP 27@33q8jcf045 33/17}.;~SBSJ 27@29q3jcd0u 31/17}<;~SBSM 27@VRB02jce017 25/21}-;~SBSP 27@VRB03jcd0u 31/14}=;~SBSR 27@28q4jcd025f035 32/16}.;~SBUG 27@24q9jcgq8 21/s}.;~SBUL 27@05q6jcd0t t/12}>;~SBUR 27@34q6jce042 32/15}=;~SBVH 27@04q1jce0t t/22}<;~SBAC;~SBAE;~SBAR;~SBAT;~SBBE;~SBBP;~SBBV;~SBCI;~SBCJ;~SBCZ;~SBDB;~SBEG;~SBFN;~SBFZ;~SBGM;~SBHT;~SBIH;~SBIL;~SBIZ;~SBJA;~SBJC;~SBJD;~SBJH;~SBJI;~SBJP;~SBKG;~SBMA;~SBMI;~SBMO;~SBMQ;~SBMS;~SBMY;~SBNV;~SBOI;~SBPB;~SBPJ;~SBPL;~SBPS;~SBPV;~SBRB;~SBRF;~SBSG;~SBSI;~SBSL;~SBSN;~SBSV;~SBTE;~SBTF;~SBTG;~SBTK;~SBTT;~SBTV;~SBUA;~SBVC;~SBVT;~SDAG;~SDCO;~SDIY;~SNBR;~SNDV;~SNGI;~SNHS;~SSKW;~SWGN;~SWKO;~SWPI;~SBAU;~SBCA;~SBCH;~SBCX;~SBDO;~SBEK;~SBGV;~SBIT;~SBJU;~SBLP;~SBML;~SBPF;~SBPG;~SBPO;~SBRD;~SBSO;~SBTB;~SBTD;~SBUF;~SBVG;~SBZM;~SNPD;~SNVB;~SNZR;~SSGG;~SSUM;~SWLC;~ZULU 2021-03-27 17:03:29;~SATZ 2021-03-27 15:30:00;~LIGZ 2021-03-27 17:03:14;~2361910031$|63w2W7wW17w|62w4W5wW18w|62w4W6wW17w|64wW25w$|y65w2W22w|y48w2W12w5W22w|g67w2W20w|68w2W20w|g67wWwW19w|gyg87w|wg50wW37w|2g11wgwg36wW37w|y12w3g36wW37w;~23619145|g12w3gw2g33w2W36w|g13w3gyg33w2W36w|y13w5g34wW36w|15w4gyg31wW37w|15w2gy2g18wW10w4W37w|16wgyw3g27w3W38w|18wg2yg28w3W37w|18w3yg29w2W2w2W2w2W29w|17w3g2y37w2W15wW13w;~23619154|18w2g2y31wW5wW15wW14w|20w2yg9wW18wW2wW11w2W6wW15w|21wy2g7w2W33w2W2w2WwW16w|21w3g21wW6wW17w2W2wW15w|21wg2y20w2W7wW6wW9w2WwW16w|22wgy20w3W6w2W5wW5wW6wW16w;~23619160|46wW5w3W11wW23w|51w4W35w|g50w4W35w|g50w3W36w|2g50wW37w|2g47wW40w|2g3w2g41w2W40w|2g3wg84w|g3wg85w|4gw2g29wW20wW12wW19w|7g28w3W24w2W26w|8g28w2W25w3W24w;~23619172|8g28w3W22w5W24w|2w5g30w2W20w5W26w|4w3g53w5W25w|4wgy3g53w3W5w3W17w|2y2gw6g15w2W35w2W6w2W17w|5ygy4g15w2W34w2W8wW17w|4y2gygw2g37wW20w2W2wW16w|7y2gw2g14wW17w2Ww2W20w3W2wW15w;~23619180|5ygyg3w2gW13w2WwW14w4W22w3W16w|5yg2y5gGg12w2W2wW14wWw4W20w2W16w|r4y2gy7g31wW2w3W13w2W23w|g3y3g2y6gw2g22w3g2w2W3w3W12wW24w|10y10g18w3g5wW2g2wW38w;~23619185|10y4g3y3g18w2g6w2gG2wg38w|y2g7y5gy4g18wg5wW3G2yg39w|10y13g15w2gwgwGWGgY4y38w|12y11g15w8g5yr38w|4y2r6y11g6wW8w3gy3g4y3rw2g35w;" }
 ],
 "profile":{
  "name":"typicode"
 }
}